structml/__init__.py
structml/line_heal.py
structml-0.0.4.dist-info/LICENSE
structml-0.0.4.dist-info/METADATA
structml-0.0.4.dist-info/WHEEL
structml-0.0.4.dist-info/top_level.txt
structml-0.0.4.dist-info/RECORD
